ccp4/__init__.py
ccp4/bibtex.py
ccp4/ccp4_200.png
ccp4/constants.py
ccp4/convert.py
ccp4/protocols.conf
ccp4/protocols/__init__.py
ccp4/protocols/protocol_coot.py
ccp4/protocols/protocol_refmac.py
ccp4/protocols/refmac_template_map2mtz.py
ccp4/protocols/refmac_template_refine.py
ccp4/tests/__init__.py
ccp4/tests/test_protocol_coot_refmac.py
ccp4/viewers/__init__.py
ccp4/viewers/viewer_coot.py
ccp4/viewers/viewer_refmac.py
scipion_em_ccp4-3.2.0.dist-info/LICENSE
scipion_em_ccp4-3.2.0.dist-info/METADATA
scipion_em_ccp4-3.2.0.dist-info/WHEEL
scipion_em_ccp4-3.2.0.dist-info/entry_points.txt
scipion_em_ccp4-3.2.0.dist-info/top_level.txt
scipion_em_ccp4-3.2.0.dist-info/RECORD
