Metadata-Version: 2.1
Name: scipion-em-ccp4
Version: 3.2.0
Summary: CCP4 model building programs in Scipion. Warning: Install CCP4 v. 7.0.56 or higher
Home-page: https://github.com/scipion-em/scipion-em-ccp4
Author: Roberto Marabini and Marta Martinez
Author-email: scipion@cnb.csic.es
License: UNKNOWN
Keywords: scipion cryoem imageprocessing scipion-3.0
Platform: UNKNOWN
Classifier: Programming Language :: Python :: 3
Requires-Dist: scipion-em-chimera (>=3.0.1)
